netiob/settings.py
netiob/tandem/__init__.py
netiob/tandem/helper.py
netiob/utils/__init__.py
netiob/utils/bgpredgraph.py
netiob/utils/calculators.py
netiob/utils/cgmdataprocessor.py
netiob/utils/coreutils.py
netiob/utils/openapsprediction.py
netiob/utils/preprocessors.py
netiob-0.1.26.dist-info/licenses/LICENSE
netiob-0.1.26.dist-info/METADATA
netiob-0.1.26.dist-info/WHEEL
netiob-0.1.26.dist-info/top_level.txt
netiob-0.1.26.dist-info/RECORD
