Metadata-Version: 2.4
Name: netiob
Version: 0.1.26
Summary: NET IOB
License-File: LICENSE
Requires-Dist: numpy>=1.22.0
Requires-Dist: pandas>=1.3.0
Requires-Dist: requests>=2.25.0
Requires-Dist: python-decouple>=3.6
Dynamic: license-file
